oarepo_communities/__init__.py
oarepo_communities/config.py
oarepo_communities/errors.py
oarepo_communities/ext.py
oarepo_communities/ext_config.py
oarepo_communities/identity_to_entity_references.py
oarepo_communities/proxies.py
oarepo_communities/utils.py
oarepo_communities/workflow.py
oarepo_communities/cf/__init__.py
oarepo_communities/cf/workflows.py
oarepo_communities/cli/__init__.py
oarepo_communities/datastreams/__init__.py
oarepo_communities/datastreams/transformers.py
oarepo_communities/fixtures/__init__.py
oarepo_communities/fixtures/catalogue.yaml
oarepo_communities/fixtures/community-types.yaml
oarepo_communities/i18n/__init__.py
oarepo_communities/i18n/webpack.py
oarepo_communities/i18n/semantic-ui/translations/oarepo_communities/i18next.js
oarepo_communities/i18n/semantic-ui/translations/oarepo_communities/messages/index.js
oarepo_communities/i18n/semantic-ui/translations/oarepo_communities/messages/cs/LC_MESSAGES/translations.json
oarepo_communities/i18n/semantic-ui/translations/oarepo_communities/messages/en/LC_MESSAGES/translations.json
oarepo_communities/i18n/translations/messages.mo
oarepo_communities/i18n/translations/messages.pot
oarepo_communities/i18n/translations/cs/LC_MESSAGES/messages.mo
oarepo_communities/i18n/translations/cs/LC_MESSAGES/messages.po
oarepo_communities/i18n/translations/en/LC_MESSAGES/messages.mo
oarepo_communities/i18n/translations/en/LC_MESSAGES/messages.po
oarepo_communities/notifications/__init__.py
oarepo_communities/notifications/generators.py
oarepo_communities/records/__init__.py
oarepo_communities/records/systemfields/__init__.py
oarepo_communities/records/systemfields/communities.py
oarepo_communities/requests/__init__.py
oarepo_communities/requests/migration.py
oarepo_communities/requests/remove_secondary.py
oarepo_communities/requests/submission_secondary.py
oarepo_communities/resolvers/__init__.py
oarepo_communities/resolvers/communities.py
oarepo_communities/resolvers/ui.py
oarepo_communities-5.4.5.dist-info/licenses/LICENSE
oarepo_communities-5.4.5.dist-info/METADATA
oarepo_communities-5.4.5.dist-info/WHEEL
oarepo_communities-5.4.5.dist-info/entry_points.txt
oarepo_communities-5.4.5.dist-info/top_level.txt
oarepo_communities-5.4.5.dist-info/RECORD
