Metadata-Version: 2.4
Name: oarepo-communities
Version: 5.4.5
License-File: LICENSE
Requires-Dist: oarepo-runtime
Requires-Dist: oarepo-requests
Requires-Dist: oarepo-workflows
Requires-Dist: oarepo-global-search
Requires-Dist: cachetools
Provides-Extra: tests
Requires-Dist: pytest-oarepo; extra == "tests"
Requires-Dist: oarepo-rdm; extra == "tests"
Requires-Dist: oarepo-vocabularies; extra == "tests"
Dynamic: license-file
